yesworkflow/__init__.py
yesworkflow/_version.py
yesworkflow-0.0.1.dist-info/METADATA
yesworkflow-0.0.1.dist-info/WHEEL
yesworkflow-0.0.1.dist-info/top_level.txt
yesworkflow-0.0.1.dist-info/RECORD
